{
  "00001": "tZozHdSs9WQ",
  "00002": "7puAydZ5Fbo",
  "00003": "17t7SEsoKfE",
  "00004": "K3syk2VOmRw",
  "00005": "EFWmcBHQ8UU",
  "00006": "t5Uq1wV4PUQ",
  "00007": "PMXjC6ZpNr4",
  "00008": "tP0zj220CbQ",
  "00009": "VVqXLXMch9g",
  "00010": "zJy2fHZiDXY",
  "00011": "KGmgHjSX0wY",
  "00012": "NtvoxOIQ9g0",
  "00013": "PSP-S882RKc",
  "00014": "sIIEP6pVACA",
  "00015": "-qleBCzkxic",
  "00016": "Lj0YUDSGg0Q",
  "00017": "Ll9Q-42Iv6Q",
  "00018": "lqd-TAabVVw",
  "00019": "F0w0--zLem0",
  "00020": "RQBgfjOROPw",
  "00021": "GJY8OMJXRAk",
  "00022": "6eW99oNNRvI",
  "00023": "z0GVXiPQC5Q",
  "00024": "iLkH6OwKUec",
  "00025": "TeNjhglXm6w",
  "00026": "G77hG3sGRDo",
  "00027": "cnRB2CgUpSw",
  "00028": "thvXWjJh7yg",
  "00029": "_EL9Fg40AP4",
  "00030": "JLaQvZHmW4Y",
  "00031": "4Fgm8KCBoEw",
  "00032": "w1RTMZCTlaQ",
  "00033": "nwrqQ2jYpwY",
  "00034": "5BkRqm9OOHk",
  "00035": "wTADOT31rnQ",
  "00036": "H6M0EulApMM",
  "00037": "GDEDQ8TCzW8",
  "00038": "xuHwv07G3qE",
  "00039": "rL46NnEf2p8",
  "00040": "hJWSZDJb-W4",
  "00041": "AVXA64MwYqE",
  "00042": "lnl9U-hHp1I",
  "00043": "sNm7WmIxgec",
  "00044": "-48dP1VwgNg",
  "00045": "Qu6F-mMAQhk",
  "00046": "Q2IeFx48Bas",
  "00047": "ZWzWL-S05fg",
  "00048": "G-vBymB7sNQ",
  "00049": "WE8QEGjBcRc",
  "00050": "C75J03JXz24",
  "00051": "rgsKm8Ib8No",
  "00052": "b8tqMLd4Jog",
  "00053": "w53GTryJ5eU",
  "00054": "AHUQdDtRaDI",
  "00055": "3nJJGqBhZlk",
  "00056": "7JFtfM9rVvQ",
  "00057": "wdOwlQZmLCk",
  "00058": "sWMk8dwljFU",
  "00059": "5sJ4oxGDqzQ",
  "00060": "NvpSsGX6pEU",
  "00061": "BciS5krYL80",
  "00062": "dgAPdpqzIbw",
  "00063": "trACvDCJCyA",
  "00064": "JlmSE3geH5o",
  "00065": "yLJb8iQUJxw",
  "00066": "c2n37UAiDuE",
  "00067": "fxHjlCBHuzA",
  "00068": "PnAD2Tb-SE8",
  "00069": "KfGHjjovIe8",
  "00070": "Xlsx_CG02UE",
  "00071": "FMtgC9lYt2w",
  "00072": "fn8JP4rUP2I",
  "00073": "4x6leDGV7gs",
  "00074": "wa9TsvMUZow",
  "00075": "3nGKFzTKY44",
  "00076": "gGUAI5FP-C0",
  "00077": "RZR7lp3zTd8",
  "00078": "wmRqLQAnwJ8",
  "00079": "wwXtPu-iA4Q",
  "00080": "GbpnAGajyMc",
  "00081": "76jauBrP2Q8",
  "00082": "JBUs7P2kIAs",
  "00083": "Frw7U5X8dhg",
  "00084": "RYQC0h-eJ4o",
  "00085": "fCQOVfOgAIQ",
  "00086": "usvTbqTHwyw",
  "00087": "Adu-EfJbuBs",
  "00088": "YfuyEdCpAp0",
  "00089": "l5x1gQxa1g4",
  "00090": "_NpsUiKBEes",
  "00091": "eIFA2ssL2Lc",
  "00092": "STIi47fPnyI",
  "00093": "cuN2M5qnALs",
  "00094": "UuliSlNeynk",
  "00095": "zokhyLQloBI",
  "00096": "wUfKbWyr-OM",
  "00097": "QgWNByQJA4A",
  "00098": "91byJDDV3mU",
  "00099": "qOwJRBi4WtU",
  "00100": "n5SRhetTxUE",
  "00101": "RxUZLmN5RsY",
  "00102": "YBdyc1WDlBQ",
  "00103": "8bNHTgVhdYM",
  "00104": "NZ3Ck43m_ZY",
  "00105": "4C2V-GiRUcw",
  "00106": "hk_OfhPTd28",
  "00107": "aUAlj1gjLLg",
  "00108": "E4OzdyxbOuU",
  "00109": "AFDOSq6Wxa0",
  "00110": "8Jtokmp8zoE",
  "00111": "EVcpKjXYa5c",
  "00112": "79vxRvYqeT4",
  "00113": "4rF7gvas7Uk",
  "00114": "Lz3S5HXyw4o",
  "00115": "UbPrlq52r7Y",
  "00116": "jUWTXq_mMjU",
  "00117": "uMaoBvGPEvI",
  "00118": "HBzyuCda2RI",
  "00119": "tYTgtsCm0DA",
  "00120": "kyohWo3aZvw",
  "00121": "WdyN1CLgRwk",
  "00122": "4qkVJixOZMk",
  "00123": "KMViJKmAV4M",
  "00124": "mVuSfxqpZa4",
  "00125": "jKU74Uns9_0",
  "00126": "DMVeh6lO2yo",
  "00127": "1fOud8Pj3ts",
  "00128": "VHK5k2ieudc",
  "00129": "HF_nIjQOIaU",
  "00130": "-jnpbEbSugQ",
  "00131": "BsCBGsKSW4g",
  "00132": "sgj04v5sDm4",
  "00133": "YIz9DxYG1t0",
  "00134": "Efa6BAWPm9o",
  "00135": "zQLfohwUsu4",
  "00136": "J47YIH1XCGE",
  "00137": "SEDEp4a8VyE",
  "00138": "NF7oYY7Lhq4",
  "00139": "gMKC5OfNJfs",
  "00140": "b5EZp76Oxhw",
  "00141": "o6nYFg2fzkU",
  "00142": "QH0Kf-7aZlw",
  "00143": "6RZhg4Fkvd0",
  "00144": "eRg15NbzqT0",
  "00145": "WmjQYFa_n50",
  "00146": "jgiNjvuTTCw",
  "00147": "1PXzYVhA2CQ",
  "00148": "nujn6wbr-e8",
  "00149": "tyd-Vs0MHH4",
  "00150": "uzaYLK3k0DQ",
  "00151": "YDswuo2dIvY",
  "00152": "DTtb9rt1tnk",
  "00153": "scdUmQBDGSU",
  "00154": "EULnIzBdr7k",
  "00155": "R__cIlBrX_Q",
  "00156": "HaEYUJ2aRHs",
  "00157": "Xs-BMEw_cRY",
  "00158": "S-4xzk26EcM",
  "00159": "0dJ30dREjaE",
  "00160": "IdfZUZ_rWCI",
  "00161": "eN3Fmpnoado",
  "00162": "cp0PV5apeNY",
  "00163": "j7NEJnxceHw",
  "00164": "LSEoQ-r_9Zw",
  "00165": "1xPCO3ruWjs",
  "00166": "1cqy4bmYOBI",
  "00167": "GqWYJT-iMTw",
  "00168": "cwXMI7zLw0k",
  "00169": "jLLrKSnbwj4",
  "00170": "NqEwn5sCxos",
  "00171": "4MKpUqLz82I",
  "00172": "tPShRhWkDvQ",
  "00173": "mX8Y_LUxIJo",
  "00174": "mhr4YecSV_Y",
  "00175": "RXT5OvdtTT0",
  "00176": "_rPIy8fNwRs",
  "00177": "VjPXdubfIG8",
  "00178": "91Niv2q4gvc",
  "00179": "9piyWrfULSk",
  "00180": "tmbEePmIFkI",
  "00181": "f_K_0SNaRk0",
  "00182": "5aKXeGNUSJs",
  "00183": "VcHkT23TY-U",
  "00184": "GGsuLVlLObc",
  "00185": "tgbYAdmb8WM",
  "00186": "DZgTN-yjVyg",
  "00187": "wfipx3OkFuo",
  "00188": "ynTRWe3J9UM",
  "00189": "5FOAd1mbtiM",
  "00190": "9aS4v5XNGFs",
  "00191": "KP6Cx9gFzVM",
  "00192": "1Qwj-HFsGx8",
  "00193": "8M3Vlnu_i3c",
  "00194": "mVw5KiGwqaQ",
  "00195": "gnUDvKEdke8",
  "00196": "ct1SIHfjzvM",
  "00197": "9c2zl-wcIRE",
  "00198": "_3M9w7WwyXU",
  "00199": "6alEBnBGdOo",
  "00200": "sWGh92O9kxU",
  "00201": "M4IGqU2hIbw",
  "00202": "OtWhohD3pIw",
  "00203": "OK848_DSj6k",
  "00204": "hq4ZF1b5lHA",
  "00205": "45V-ai4htd8",
  "00206": "vAJme94IBBg",
  "00207": "WJ5jlbtyM9M",
  "00208": "s_J-RVWhJHU",
  "00209": "ZhmLYsxhWUk",
  "00210": "RZRme62DaXE",
  "00211": "7neipvZ_H0c",
  "00212": "5cRopUrDgRQ",
  "00213": "QrqPjFyM0wg",
  "00214": "l958Bg-u1Rk",
  "00215": "jRqhGC5vgC0",
  "00216": "63UbxFkHepo",
  "00217": "ilottRbDnGY",
  "00218": "W5tMG04efxs",
  "00219": "273U9MXaz40",
  "00220": "LB5uhCKrzVI",
  "00221": "At_ykyi1ad8",
  "00222": "4ujBQOzs6Lw",
  "00223": "hBLCzHnnj10",
  "00224": "jF5vUrJFp5Q",
  "00225": "f1zLSpzCh9E",
  "00226": "-95NVeFwZYU",
  "00227": "c0dvabcWVo0",
  "00228": "_SU__KLiPCc",
  "00229": "OCLgRVRLZXo",
  "00230": "6c7Q4hjcBjA",
  "00231": "ym6GBXy6mnc",
  "00232": "uGi-q0irHlE",
  "00233": "Ys3MlXA9cqs",
  "00234": "PNoIn1WKiEc",
  "00235": "gvLMhpzYic0",
  "00236": "r-kV2btEUaw",
  "00237": "KqBZAxCfWHA",
  "00238": "cakuOGmna7I",
  "00239": "98B9ZHOlk2E",
  "00240": "H2dACACnPo4",
  "00241": "V3qUoiwr5kQ",
  "00242": "WGMJ8GFGP8E",
  "00243": "wIiVp3poe2c",
  "00244": "AyympmxCbzU",
  "00245": "QBDem6bffyo",
  "00246": "A93OQy81TYs",
  "00247": "szwC9CJWd5U",
  "00248": "_C2vqI9FVwg",
  "00249": "Ue2KkI3DLhU",
  "00250": "x_XS5q0EUQs",
  "00251": "2Az_Ux2uNmk",
  "00252": "lYBUbBu4W08",
  "00253": "VVPFfjYaTpw",
  "00254": "b52HCuCSMPo",
  "00255": "1L3XxUxEb6U",
  "00256": "4e_ufgBigNM",
  "00257": "X8JH6npiSC4",
  "00258": "2DtevH2Lw2I",
  "00259": "bRXTMuH2WVc",
  "00260": "pJQmn1lUFq4",
  "00261": "qBhsLq9FG4E",
  "00262": "ovL5LIhp-Qs",
  "00263": "_0AVOVzKUPY",
  "00264": "HmfPiXTNVso",
  "00265": "NNiTxUEnmKI",
  "00266": "C2e4Idh6HME",
  "00267": "RQRxVpCWTr4",
  "00268": "NLSq2PV2WNg",
  "00269": "9EHFTJvnDlg",
  "00270": "SbenaOqv4yQ",
  "00271": "zS_O0xHOsGM",
  "00272": "ggJI9dKBk48",
  "00273": "PBx3yjRmGVA",
  "00274": "E7zmRvhFEYo",
  "00275": "63Ie13S3U0s",
  "00276": "wDlKTQ3Ig7A",
  "00277": "sXA5OILKitY",
  "00278": "SYUg9LgV2No",
  "00279": "xNDRrpG1Gc4",
  "00280": "RN8Li7kYNnw",
  "00281": "RDbL8GLr1yw",
  "00282": "wnWxeBfV2ZQ",
  "00283": "5S6CLq6ENWs",
  "00284": "_dbYxAr697w",
  "00285": "If8px-yUBeI",
  "00286": "HmXO6ubblIA",
  "00287": "QNwCP2vg0mI",
  "00288": "G4j-ndFkrm4",
  "00289": "d9jhDwxt22Y",
  "00290": "X84vTQnuP_s",
  "00291": "RmYCOm4ehKs",
  "00292": "QPzOeESWG5o",
  "00293": "iR8IgoAmH_4",
  "00294": "HqM7g4jH5Hk",
  "00295": "FRlTjErEDPQ",
  "00296": "wXzpgSEOiTs",
  "00297": "98rKktwzzC8",
  "00298": "ypWXEnK_0T8",
  "00299": "-eGM0IJc70Y",
  "00300": "O6q3JRMlh-I",
  "00301": "bkT4bBQJAKA",
  "00302": "rbHOornfq-s",
  "00303": "Fd_3EkGr0-4",
  "00304": "UGug8QWOAQ0",
  "00305": "YBCF5gyyH3Y",
  "00306": "jwikdkqYw6o",
  "00307": "CVsLEI-hCXw",
  "00308": "c2S1x2kTYJM"
}